urllib3_sigv4/__init__.py
urllib3_sigv4/py.typed
urllib3_sigv4-1.1.0.dist-info/METADATA
urllib3_sigv4-1.1.0.dist-info/WHEEL
urllib3_sigv4-1.1.0.dist-info/licenses/LICENSE
urllib3_sigv4-1.1.0.dist-info/RECORD
