Metadata-Version: 2.4
Name: urllib3_sigv4
Version: 1.1.0
Summary: Extension to urllib3 adding support for AWS Signature Version 4
Project-URL: Homepage, https://github.com/tlinhart/urllib3-sigv4
Author-email: Tomáš Linhart <pasmen@gmail.com>
License-Expression: MIT
License-File: LICENSE
Keywords: aws,sigv4,urllib
Classifier: Operating System :: OS Independent
Classifier: Programming Language :: Python :: 3
Classifier: Topic :: Internet :: WWW/HTTP
Classifier: Topic :: Software Development :: Libraries
Requires-Python: >=3.9
Requires-Dist: boto3<2.0.0,>=1.3.1
Requires-Dist: urllib3<3.0.0,>=2.0.0
